{
  "title": "원문의 6 승수 기반 생성적 최적해 탐색 실험",
  "description": "값 배치 P_t에 v(P_t) = 6*t mod 271을 강제하고, P_t가 격자 상에서 연속적인 이동(1-step)을 이루도록 제약을 걸어 역사적 원본 도안을 추정함.",
  "results": {
    "no_constraint": {
      "penalty": 6.0,
      "avg_distance": 9.063197026022305
    },
    "constrained": {
      "penalty": 38.0,
      "avg_distance": 3.278810408921933
    }
  },
  "verdict": "수학적 벌점 하한(6.0)과 격자 연속성(평균 거리 1.0~2.0)을 동시에 만족하는 해는 존재하지 않음. 기하학적 연속성 제약을 가할수록 벌점이 기하급수적으로 상승함. 이는 저자 본인의 최적해 역시 단순한 6-step Hamiltonian path 형태가 아니었음을 의미하며, 원문의 '添六'은 배치 규칙이 아닌 면적 산출 계산식의 일부였음을 재차 방증함."
}